rtsgame/App.py
rtsgame/MainMenu.py
rtsgame/__init__.py
rtsgame/client-shell.py
rtsgame/src/__init__.py
rtsgame/src/Client/Animation.py
rtsgame/src/Client/Camera.py
rtsgame/src/Client/EntitySprite.py
rtsgame/src/Client/Game.py
rtsgame/src/Client/HPBar.py
rtsgame/src/Client/MainWindow.py
rtsgame/src/Client/SIOServer.py
rtsgame/src/Client/Sprite.py
rtsgame/src/Client/TextWidget.py
rtsgame/src/Client/TextWindow.py
rtsgame/src/Client/TileSprite.py
rtsgame/src/Client/__init__.py
rtsgame/src/Client/HUD/Defence/Defence_Flash_0.png
rtsgame/src/Client/HUD/Defence/Defence_Flash_1.png
rtsgame/src/Client/HUD/Defence/Defence_Flash_2.png
rtsgame/src/Client/HUD/Defence/Defence_Flash_3.png
rtsgame/src/Client/HUD/Defence/Value/Defence_Value_0.png
rtsgame/src/Client/HUD/Defence/Value/Defence_Value_1.png
rtsgame/src/Client/HUD/Defence/Value/Defence_Value_2.png
rtsgame/src/Client/HUD/Defence/Value/Defence_Value_3.png
rtsgame/src/Client/HUD/Defence/Value/Defence_Value_4.png
rtsgame/src/Client/HUD/Defence/Value/Defence_Value_5.png
rtsgame/src/Client/HUD/HP/HP_Flash_0.png
rtsgame/src/Client/HUD/HP/HP_Flash_1.png
rtsgame/src/Client/HUD/HP/HP_Flash_2.png
rtsgame/src/Client/HUD/HP/HP_Flash_3.png
rtsgame/src/Client/HUD/HP/Value/HP_Value_0.png
rtsgame/src/Client/HUD/HP/Value/HP_Value_1.png
rtsgame/src/Client/HUD/HP/Value/HP_Value_2.png
rtsgame/src/Client/HUD/HP/Value/HP_Value_3.png
rtsgame/src/Client/HUD/HP/Value/HP_Value_4.png
rtsgame/src/Client/HUD/HP/Value/HP_Value_5.png
rtsgame/src/Client/Items/Axe/Axe_0.png
rtsgame/src/Client/Items/Axe/Axe_1.png
rtsgame/src/Client/Items/Axe/Axe_2.png
rtsgame/src/Client/Items/Axe/Axe_3.png
rtsgame/src/Client/Items/Defence/Defence_0.png
rtsgame/src/Client/Items/Defence/Defence_1.png
rtsgame/src/Client/Items/Defence/Defence_2.png
rtsgame/src/Client/Items/Defence/Defence_3.png
rtsgame/src/Client/Items/HP/HP_0.png
rtsgame/src/Client/Items/HP/HP_1.png
rtsgame/src/Client/Items/HP/HP_2.png
rtsgame/src/Client/Items/HP/HP_3.png
rtsgame-0.12.dist-info/METADATA
rtsgame-0.12.dist-info/WHEEL
rtsgame-0.12.dist-info/entry_points.txt
rtsgame-0.12.dist-info/top_level.txt
rtsgame-0.12.dist-info/RECORD
