Metadata-Version: 2.1
Name: rtsgame
Version: 0.12
Summary: The funniest rts in the world
Home-page: https://github.com/ashat1701/rts-game
Author: Mega team
Author-email: harmoning.moagic@ya.ru
License: MIT
Platform: UNKNOWN
Classifier: Development Status :: 3 - Alpha
Classifier: License :: OSI Approved :: MIT License
Classifier: Programming Language :: Python :: 3
Requires-Dist: pygame
Requires-Dist: eventlet
Requires-Dist: greenlet
Requires-Dist: python-engineio
Requires-Dist: requests
Requires-Dist: websocket-client
Requires-Dist: python-socketio
